pythed/__init__.py
pythed/app/Vinted.py
pythed/app/__init__.py
pythed/app/api/__init__.py
pythed/app/api/brand.py
pythed/app/api/items.py
pythed/app/api/shipping_details.py
pythed/app/api/sizes.py
pythed/app/api/status.py
pythed/app/api/users.py
pythed/app/config/__init__.py
pythed/app/config/brands.json
pythed/app/config/colors.json
pythed/app/config/endpoints.json
pythed/app/config/materials.json
pythed/app/config/sizes.json
pythed/app/config/status.json
pythed/app/tests/__init__.py
pythed/app/tests/brands/__init__.py
pythed/app/tests/brands/test_get_all_brands.py
pythed/app/tests/brands/test_get_brand.py
pythed/app/tests/items/__init__.py
pythed/app/tests/items/test_get_item_details.py
pythed/app/tests/items/test_get_shipping_details.py
pythed/app/tests/items/test_search_items.py
pythed/app/tests/items/test_similar_items.py
pythed/app/tests/users/__init__.py
pythed/app/tests/users/test_get_user_info.py
pythed/app/tests/users/test_get_user_reviews.py
pythed/app/utils/__init__.py
pythed/app/utils/config_functions.py
pythed/app/utils/cookies.py
pythed-0.0.5.dist-info/METADATA
pythed-0.0.5.dist-info/WHEEL
pythed-0.0.5.dist-info/top_level.txt
pythed-0.0.5.dist-info/RECORD
