Metadata-Version: 2.1
Name: pythed
Version: 0.0.5
Summary: A vinted api wrapper in python.
Author: Archithebald
Author-email: <archithebald@proton.me>
Keywords: python,vinted,pypi,api,wrapper
Requires-Dist: requests
Requires-Dist: selenium
